smartscout/__init__.py
smartscout/client.py
smartscout/exceptions.py
smartscout/models/__init__.py
smartscout/models/base.py
smartscout/models/enums.py
smartscout/models/requests.py
smartscout/models/responses.py
smartscout_api-0.1.1.dist-info/LICENSE
smartscout_api-0.1.1.dist-info/METADATA
smartscout_api-0.1.1.dist-info/WHEEL
smartscout_api-0.1.1.dist-info/top_level.txt
smartscout_api-0.1.1.dist-info/RECORD
