Metadata-Version: 2.1
Name: smartscout-api
Version: 0.1.1
Summary: A Python client for the SmartScout API
Home-page: https://github.com/weisberg/smartscout-api-python
Author: Brian Weisberg
Author-email: profs-brownie.0g@icloud.com
Classifier: Development Status :: 3 - Alpha
Classifier: Intended Audience :: Developers
Classifier: License :: OSI Approved :: MIT License
Classifier: Programming Language :: Python :: 3
Classifier: Programming Language :: Python :: 3.7
Classifier: Programming Language :: Python :: 3.8
Classifier: Programming Language :: Python :: 3.9
License-File: LICENSE
Requires-Dist: requests >=2.25.0
Requires-Dist: pydantic >=1.8.0
